peblarpy/__init__.py
peblarpy/api.py
peblarpy/const.py
peblarpy/util.py
peblarpy-0.0.1.dist-info/LICENSE
peblarpy-0.0.1.dist-info/METADATA
peblarpy-0.0.1.dist-info/WHEEL
peblarpy-0.0.1.dist-info/top_level.txt
peblarpy-0.0.1.dist-info/RECORD
