Metadata-Version: 2.1
Name: peblarpy
Version: 0.0.1
Summary: Python Client to Peblar EVCC REST-API
Home-page: https://github.com/wyleung/peblarpy
Author: wyleung
License: MIT License
Project-URL: Homepage, https://github.com/wyleung/peblarpy
License-File: LICENSE
Requires-Dist: aiohttp >=3.9.4
